ctypes_callable.py
ctypes_callable-1.0.4.dist-info/LICENSE
ctypes_callable-1.0.4.dist-info/METADATA
ctypes_callable-1.0.4.dist-info/WHEEL
ctypes_callable-1.0.4.dist-info/top_level.txt
ctypes_callable-1.0.4.dist-info/RECORD
