Metadata-Version: 1.1
Name: ctypes-callable
Version: 1.0.4
Summary: Implements ``callable`` using ctypes (useful on CPython 3.0 and 3.1).
Home-page: https://github.com/mentalisttraceur/python-ctypes-callable
Author: Alexander Kozhevnikov
Author-email: mentalisttraceur@gmail.com
License: 0BSD
Platform: UNKNOWN
Classifier: Development Status :: 6 - Mature
Classifier: Programming Language :: Python :: 3
Classifier: Programming Language :: Python :: 2
Classifier: Programming Language :: Python :: Implementation :: CPython
Classifier: Operating System :: OS Independent
